{
  "uses": [
    {
      "category": "Development",
      "items": [
        {
          "name": "Vim",
          "url": "https://www.vim.org/",
          "description": "As a keyboard junkie, Vim suits my needs very well. After dipping my toes in with \"Vim-Mode\" in other editors, I finally made the jump years ago and haven't looked back."
        },
        {
          "name": "iTerm2",
          "url": "https://iterm2.com/",
          "description": "My preferred terminal emulator."
        },
        {
          "name": "Cobalt2 theme",
          "url": "https://github.com/wesbos/Cobalt2-iterm",
          "description": "My favorite color scheme. 💙💛"
        },
        {
          "name": "JetBrains Mono font",
          "url": "https://www.jetbrains.com/lp/mono/",
          "description": "Recent addition, but into it so far. Bonus points for being free and open source."
        },
        {
          "name": "my dotfiles",
          "url": "https://github.com/djpowers/dotfiles",
          "description": "I try to keep anything else configurable in my dotfiles."
        }
      ]
    },
    {
      "category": "Writing",
      "items": [
        {
          "name": "Ulysses",
          "url": "https://ulysses.app/",
          "description": "I do all of my prose writing in Ulysses. I have groups set up to track progress of different pieces. Writing in Markdown is a must for me, and its comment feature is a game-changer for me. That along with writing goals and reliable sync between devices make it an ideal solution for writing."
        },
        {
          "name": "Byword",
          "url": "https://bywordapp.com/",
          "description": "For quick one-off documents, I may reach for Byword. Markdown support included."
        }
      ]
    },
    {
      "category": "Hosting",
      "items": [
        {
          "name": "Digital Ocean",
          "url": "https://m.do.co/c/53fdcc742fa0",
          "description": "New to the platform, but their Droplet system makes getting started much easier (or just possible in the first place). (Note: referral link)"
        },
        {
          "name": "Netlify",
          "url": "https://www.netlify.com/",
          "description": "For static sites (like this one), Netlify is great. Rock solid deployment process, and they do a lot for the community as well."
        },
        {
          "name": "Heroku",
          "url": "https://www.heroku.com/",
          "description": "For a project with a back-end where I don't want to worry about server infrastructure Heroku is perfect."
        },
        {
          "name": "Namecheap",
          "url": "https://www.namecheap.com/",
          "description": "When buying domain names, I've gone with Namecheap. Some of the cheapest prices around, but from a reputable company."
        }
      ]
    },
    {
      "category": "Productivity",
      "items": [
        {
          "name": "Firefox",
          "url": "https://www.mozilla.org/en-US/firefox/browsers/",
          "description": "Switch back to Firefox after a decade-long hiatus, and happy to see it's still on par with other major browsers. The built-in privacy features (combined with Mozilla's commitment to an open web) definitely make it worth giving Firefox another look."
        },
        {
          "name": "Things",
          "url": "https://culturedcode.com/things/",
          "description": "The best to-do app I've used, hands down. Beautiful design and tons of attention has been given to each feature."
        },
        {
          "name": "Alfred",
          "url": "https://www.alfredapp.com/",
          "description": "I use Alfred for every web search, as a quick dictionary, and to control Spotify. Super versatile and extensible."
        },
        {
          "name": "1Password",
          "url": "https://1password.com/",
          "description": "Been using this password manager forever. If not this one, please find one you like."
        },
        {
          "name": "Mailplane",
          "url": "https://mailplaneapp.com/",
          "description": "A native application wrapper around the Gmail interface."
        },
        {
          "name": "Fantastical",
          "url": "https://flexibits.com/fantastical",
          "description": "An excellent calendar application."
        },
        {
          "name": "Backblaze",
          "url": "https://secure.backblaze.com/r/00grp4",
          "description": "Off-site backup is a necessity, and Backblaze has saved me a number of times. (Note: referral link)"
        },
        {
          "name": "Dash",
          "url": "https://kapeli.com/dash",
          "description": "A handy resource to quickly look up development documentation."
        },
        {
          "name": "SelfControl",
          "url": "https://selfcontrolapp.com/",
          "description": "Easily block the websites that are ingrained in your muscle memory."
        }
      ]
    },
    {
      "category": "Browser Extensions",
      "items": [
        {
          "name": "Vimium",
          "url": "https://vimium.github.io/",
          "description": "Keeps my hands on the keyboard while in my browser. Strong recommend if you already use Vim, or even if you don't."
        },
        {
          "name": "1Password",
          "url": "https://support.1password.com/1password-extension/",
          "description": "Easily autofill your logins in the browser."
        },
        {
          "name": "uBlock Origin",
          "url": "https://getublock.com/",
          "description": "Best ad blocker in the biz."
        },
        {
          "name": "Privacy Badger",
          "url": "https://www.eff.org/privacybadger",
          "description": "Complements a privacy blocklist well by identifying trackers as you browse and denying them."
        },
        {
          "name": "HTTPS Everywhere",
          "url": "https://www.eff.org/https-everywhere",
          "description": "Most sites are using HTTPS now, but force it if needed."
        },
        {
          "name": "Decentraleyes",
          "url": "https://decentraleyes.org/",
          "description": "Will improve performance by caching CDN data, and preserving privacy whilst doing so. A win-win."
        },
        {
          "name": "Wappalyzer",
          "url": "https://www.wappalyzer.com/download",
          "description": "Curiosity gets the best of me while browsing, and this lets me keep my finger on the pulse of what technologies other people are using to build web applications."
        },
        {
          "name": "Terms of Service; Didn’t Read",
          "url": "https://tosdr.org/downloads.html",
          "description": "You know you don't read privacy policies, so it's nice to get alerted if there are any red flags as you browse."
        },
        {
          "name": "Facebook Container",
          "url": "https://blog.mozilla.org/firefox/facebook-container-extension/",
          "description": "A Firefox exclusive, which I could argue is reason enough to switch. Isolates your browsing so that Facebook can't creepily follow you around the net."
        },
        {
          "name": "FB Purity",
          "url": "https://www.fbpurity.com/",
          "description": "Interface is ugly as sin, but allows you to block the annoying parts of Facebook."
        },
        {
          "name": "Old Reddit Redirect",
          "url": "https://github.com/tom-james-watson/old-reddit-redirect",
          "description": "For the rare times I find myself on Reddit, this makes the interface tolerable."
        },
        {
          "name": "Video Speed Controller",
          "url": "https://github.com/igrigorik/videospeed",
          "description": "Convenient video controls that work on any site."
        },
        {
          "name": "Metastream",
          "url": "https://getmetastream.com/",
          "description": "Remote streaming parties for almost any platform."
        }
      ]
    }
  ]
}
